zaoshu/__init__.py
zaoshu/zaoshu.py
zaoshu/zaoshu_test.py
zaoshu-0.2.0.dist-info/DESCRIPTION.rst
zaoshu-0.2.0.dist-info/METADATA
zaoshu-0.2.0.dist-info/RECORD
zaoshu-0.2.0.dist-info/WHEEL
zaoshu-0.2.0.dist-info/metadata.json
zaoshu-0.2.0.dist-info/top_level.txt
